smartbill/__init__.py
smartbill/client.py
smartbill/models.py
smartbill/templates.py
smartbill/version.py
smartbill/xsd.py
Smartbill.py-0.0.6.dist-info/LICENSE
Smartbill.py-0.0.6.dist-info/METADATA
Smartbill.py-0.0.6.dist-info/WHEEL
Smartbill.py-0.0.6.dist-info/top_level.txt
Smartbill.py-0.0.6.dist-info/RECORD
