Metadata-Version: 2.1
Name: Smartbill.py
Version: 0.0.6
Summary: Smartbill Connector
Author-email: Andrej Granec <granec@awinter.sk>
Project-URL: Homepage, https://github.com/awinter/smartbill
Project-URL: Issues, https://github.com/pypa/smartbill/issues
Classifier: Programming Language :: Python :: 3
Classifier: License :: OSI Approved :: MIT License
Classifier: Operating System :: OS Independent
Requires-Python: >=3.8
License-File: LICENSE
